vpn_controller/__init__.py
vpn_controller/vpn.py
vpn_controller-1.0.0.dist-info/METADATA
vpn_controller-1.0.0.dist-info/WHEEL
vpn_controller-1.0.0.dist-info/top_level.txt
vpn_controller-1.0.0.dist-info/RECORD
