Metadata-Version: 2.4
Name: vpn-controller
Version: 1.0.0
Summary: Minimal OpenVPN connection manager for ProtonVPN - WSL-optimized
Author-email: CCerrer <boymetatron@gmail.com>
License: MIT
Project-URL: Homepage, https://github.com/CCerrer/vpn-controller
Project-URL: Repository, https://github.com/CCerrer/vpn-controller
Project-URL: Issues, https://github.com/CCerrer/vpn-controller/issues
Keywords: vpn,openvpn,protonvpn,wsl,windows
Classifier: Development Status :: 4 - Beta
Classifier: Intended Audience :: Developers
Classifier: License :: OSI Approved :: MIT License
Classifier: Programming Language :: Python :: 3
Classifier: Programming Language :: Python :: 3.6
Classifier: Programming Language :: Python :: 3.7
Classifier: Programming Language :: Python :: 3.8
Classifier: Programming Language :: Python :: 3.9
Classifier: Programming Language :: Python :: 3.10
Classifier: Programming Language :: Python :: 3.11
Classifier: Operating System :: POSIX :: Linux
Classifier: Topic :: System :: Networking
Requires-Python: >=3.6
Requires-Dist: requests>=2.25.0
